seed_cli/__init__.py
seed_cli/apply.py
seed_cli/capture.py
seed_cli/checksums.py
seed_cli/cli.py
seed_cli/diff.py
seed_cli/doctor.py
seed_cli/executor.py
seed_cli/exporter.py
seed_cli/graphviz.py
seed_cli/hooks.py
seed_cli/image.py
seed_cli/includes.py
seed_cli/lock_heartbeat.py
seed_cli/logging.py
seed_cli/match.py
seed_cli/parsers.py
seed_cli/planning.py
seed_cli/schema.py
seed_cli/snapshot.py
seed_cli/spec_history.py
seed_cli/structure_lock.py
seed_cli/sync.py
seed_cli/template_registry.py
seed_cli/templates.py
seed_cli/templating.py
seed_cli/ui.py
seed_cli/plugins/__init__.py
seed_cli/plugins/base.py
seed_cli/plugins/loader.py
seed_cli/resources/seed.schema.json
seed_cli/resources/default_templates/fastapi/source.json
seed_cli/resources/default_templates/node-typescript/source.json
seed_cli/resources/default_templates/python-package/source.json
seed_cli/state/__init__.py
seed_cli/state/base.py
seed_cli/state/http.py
seed_cli/state/local.py
seed_cli/utils/__init__.py
seed_cli/utils/dir.py
seed_cli/utils/verify-tree.py
seed_cli-1.0.5.dist-info/METADATA
seed_cli-1.0.5.dist-info/WHEEL
seed_cli-1.0.5.dist-info/entry_points.txt
seed_cli-1.0.5.dist-info/licenses/LICENSE.md
seed_cli-1.0.5.dist-info/RECORD
