Metadata-Version: 2.4
Name: seed-cli
Version: 1.0.5
Summary: The perfect pair for the `tree` program. Seed creates, updates and deletes file and folder structures in your codebase.
Project-URL: Repository, https://github.com/isaac12x/seed-cli.git
Project-URL: Issues, https://github.com/isaac12x/seed-cli/issues
Author-email: Isaac AR <isaac@fortisvincere.com>
Maintainer-email: Isaac AR <isaac@fortisvincere.com>
License: ModifiedMIT
License-File: LICENSE.md
Keywords: directory,filesystem,orchestration,seed,terraform,tree
Classifier: Development Status :: 4 - Beta
Classifier: Intended Audience :: Developers
Classifier: License :: OSI Approved :: MIT License
Classifier: Operating System :: OS Independent
Classifier: Programming Language :: Python :: 3
Classifier: Programming Language :: Python :: 3.6
Classifier: Programming Language :: Python :: 3.7
Classifier: Programming Language :: Python :: 3.8
Classifier: Programming Language :: Python :: 3.9
Classifier: Programming Language :: Python :: 3.10
Classifier: Programming Language :: Python :: 3.11
Classifier: Programming Language :: Python :: 3.12
Classifier: Topic :: Software Development :: Build Tools
Requires-Python: >=3.10
Requires-Dist: argcomplete
Requires-Dist: pyyaml
Requires-Dist: requests
Provides-Extra: dev
Requires-Dist: black==23.3.0; extra == 'dev'
Requires-Dist: hypothesis>=6.103.1; extra == 'dev'
Requires-Dist: hypothesis[numpy]>=6.103.1; extra == 'dev'
Requires-Dist: pre-commit; extra == 'dev'
Requires-Dist: pytest; extra == 'dev'
Requires-Dist: pytest-asyncio; extra == 'dev'
Requires-Dist: pytest-cov; extra == 'dev'
Requires-Dist: rich; extra == 'dev'
Provides-Extra: image
Requires-Dist: fitz; extra == 'image'
Requires-Dist: numpy; extra == 'image'
Requires-Dist: opencv-python; extra == 'image'
Requires-Dist: pillow; extra == 'image'
Requires-Dist: pytesseract; extra == 'image'
Provides-Extra: ui
Requires-Dist: rich; extra == 'ui'
